[
{
  "directory": "C:/Users/petros/projects/ImageView/build",
  "command": "C:\\PROGRA~2\\MIB055~1\\2017\\COMMUN~1\\VC\\Tools\\MSVC\\1414~1.264\\bin\\Hostx64\\x64\\cl.exe @<<
 /nologo /TP -DQT_CORE_LIB -DQT_GUI_LIB -DQT_WIDGETS_LIB -IC:\\Users\\petros\\projects\\ImageView\\build -IC:\\Users\\petros\\projects\\ImageView -IC:\\Users\\petros\\projects\\ImageView\\build\\imageview_autogen\\include -IC:\\Qt\\5.12.0\\msvc2017_64\\include -IC:\\Qt\\5.12.0\\msvc2017_64\\include\\QtWidgets -IC:\\Qt\\5.12.0\\msvc2017_64\\include\\QtGui -IC:\\Qt\\5.12.0\\msvc2017_64\\include\\QtANGLE -IC:\\Qt\\5.12.0\\msvc2017_64\\include\\QtCore -IC:\\Qt\\5.12.0\\msvc2017_64\\.\\mkspecs\\win32-msvc  /DWIN32 /D_WINDOWS /W3 /GR /EHsc /MDd /Zi /Ob0 /Od /RTC1   /FoCMakeFiles\\imageview.dir\\src\\main.cpp.obj /FdCMakeFiles\\imageview.dir\\ /FS -c C:\\Users\\petros\\projects\\ImageView\\src\\main.cpp
<<",
  "file": "C:/Users/petros/projects/ImageView/src/main.cpp"
},
{
  "directory": "C:/Users/petros/projects/ImageView/build",
  "command": "C:\\PROGRA~2\\MIB055~1\\2017\\COMMUN~1\\VC\\Tools\\MSVC\\1414~1.264\\bin\\Hostx64\\x64\\cl.exe @<<
 /nologo /TP -DQT_CORE_LIB -DQT_GUI_LIB -DQT_WIDGETS_LIB -IC:\\Users\\petros\\projects\\ImageView\\build -IC:\\Users\\petros\\projects\\ImageView -IC:\\Users\\petros\\projects\\ImageView\\build\\imageview_autogen\\include -IC:\\Qt\\5.12.0\\msvc2017_64\\include -IC:\\Qt\\5.12.0\\msvc2017_64\\include\\QtWidgets -IC:\\Qt\\5.12.0\\msvc2017_64\\include\\QtGui -IC:\\Qt\\5.12.0\\msvc2017_64\\include\\QtANGLE -IC:\\Qt\\5.12.0\\msvc2017_64\\include\\QtCore -IC:\\Qt\\5.12.0\\msvc2017_64\\.\\mkspecs\\win32-msvc  /DWIN32 /D_WINDOWS /W3 /GR /EHsc /MDd /Zi /Ob0 /Od /RTC1   /FoCMakeFiles\\imageview.dir\\src\\imageview.cpp.obj /FdCMakeFiles\\imageview.dir\\ /FS -c C:\\Users\\petros\\projects\\ImageView\\src\\imageview.cpp
<<",
  "file": "C:/Users/petros/projects/ImageView/src/imageview.cpp"
},
{
  "directory": "C:/Users/petros/projects/ImageView/build",
  "command": "C:\\PROGRA~2\\MIB055~1\\2017\\COMMUN~1\\VC\\Tools\\MSVC\\1414~1.264\\bin\\Hostx64\\x64\\cl.exe @<<
 /nologo /TP -DQT_CORE_LIB -DQT_GUI_LIB -DQT_WIDGETS_LIB -IC:\\Users\\petros\\projects\\ImageView\\build -IC:\\Users\\petros\\projects\\ImageView -IC:\\Users\\petros\\projects\\ImageView\\build\\imageview_autogen\\include -IC:\\Qt\\5.12.0\\msvc2017_64\\include -IC:\\Qt\\5.12.0\\msvc2017_64\\include\\QtWidgets -IC:\\Qt\\5.12.0\\msvc2017_64\\include\\QtGui -IC:\\Qt\\5.12.0\\msvc2017_64\\include\\QtANGLE -IC:\\Qt\\5.12.0\\msvc2017_64\\include\\QtCore -IC:\\Qt\\5.12.0\\msvc2017_64\\.\\mkspecs\\win32-msvc  /DWIN32 /D_WINDOWS /W3 /GR /EHsc /MDd /Zi /Ob0 /Od /RTC1   /FoCMakeFiles\\imageview.dir\\imageview_autogen\\mocs_compilation.cpp.obj /FdCMakeFiles\\imageview.dir\\ /FS -c C:\\Users\\petros\\projects\\ImageView\\build\\imageview_autogen\\mocs_compilation.cpp
<<",
  "file": "C:/Users/petros/projects/ImageView/build/imageview_autogen/mocs_compilation.cpp"
}
]